alias/__init__.py
alias/plugin.py
mkdocs_alias_plugin-0.10.1.dist-info/licenses/LICENSE.md
mkdocs_alias_plugin-0.10.1.dist-info/METADATA
mkdocs_alias_plugin-0.10.1.dist-info/WHEEL
mkdocs_alias_plugin-0.10.1.dist-info/entry_points.txt
mkdocs_alias_plugin-0.10.1.dist-info/top_level.txt
mkdocs_alias_plugin-0.10.1.dist-info/RECORD
