Metadata-Version: 2.4
Name: mkdocs-alias-plugin
Version: 0.10.1
Summary: An MkDocs plugin allowing links to your pages using a custom alias
Home-page: https://github.com/eddyluten/mkdocs-alias-plugin
Author: Eddy Luten
Author-email: eddyluten@gmail.com
License: MIT
Keywords: mkdocs python markdown alias link wiki
Classifier: License :: OSI Approved :: MIT License
Classifier: Programming Language :: Python
Classifier: Programming Language :: Python :: 3 :: Only
Classifier: Topic :: Software Development :: Libraries :: Python Modules
Classifier: Topic :: Documentation
Classifier: Topic :: Text Processing
Classifier: Topic :: Text Processing :: Markup
Classifier: Topic :: Text Processing :: Markup :: Markdown
Requires-Python: >=3.0
License-File: LICENSE.md
Requires-Dist: mkdocs
Requires-Dist: markdown
Dynamic: author
Dynamic: author-email
Dynamic: classifier
Dynamic: description
Dynamic: description-content-type
Dynamic: home-page
Dynamic: keywords
Dynamic: license
Dynamic: license-file
Dynamic: requires-dist
Dynamic: requires-python
Dynamic: summary
